{
  "model_info": {
    "model_name": "v1_devclub_rf_temporal_single",
    "model_type": "RandomForestClassifier",
    "split_type": "temporal",
    "library": "scikit-learn",
    "library_version": "1.6.1",
    "trained_at": "2025-11-05T10:19:02.896711",
    "training_duration_info": "Trained with temporal split"
  },
  "hyperparameters": {
    "n_estimators": 100,
    "max_depth": 10,
    "min_samples_split": 2,
    "min_samples_leaf": 1,
    "max_features": "sqrt",
    "class_weight": "balanced",
    "random_state": 42,
    "n_jobs": -1
  },
  "training_data": {
    "dataset_name": "dataset_devclub_rf_temporal",
    "total_records": 45982,
    "training_records": 34246,
    "test_records": 11736,
    "features_count": 57,
    "target_distribution": {
      "training_positive_rate": 0.01626467324651054,
      "test_positive_rate": 0.01031015678254942,
      "training_positive_count": 557,
      "test_positive_count": 121
    },
    "temporal_split": {
      "period_start": "2025-03-01",
      "period_end": "2025-08-12",
      "cut_date": "2025-06-23",
      "training_days": 114,
      "total_days": 164
    }
  },
  "performance_metrics": {
    "auc": 0.6369627476581651,
    "top3_decil_concentration": 45.45,
    "top5_decil_concentration": 67.77,
    "lift_maximum": 1.9,
    "monotonia_percentage": 100.0,
    "baseline_conversion_rate": 0.01031015678254942
  },
  "decil_analysis": {
    "decil_1": {
      "total_leads": 1174,
      "conversions": 3,
      "conversion_rate": 0.0026,
      "pct_total_conversions": 2.48,
      "lift": 0.25
    },
    "decil_2": {
      "total_leads": 1174,
      "conversions": 3,
      "conversion_rate": 0.0026,
      "pct_total_conversions": 2.48,
      "lift": 0.25
    },
    "decil_3": {
      "total_leads": 1174,
      "conversions": 9,
      "conversion_rate": 0.0077,
      "pct_total_conversions": 7.44,
      "lift": 0.75
    },
    "decil_4": {
      "total_leads": 1173,
      "conversions": 12,
      "conversion_rate": 0.0102,
      "pct_total_conversions": 9.92,
      "lift": 0.99
    },
    "decil_5": {
      "total_leads": 1173,
      "conversions": 12,
      "conversion_rate": 0.0102,
      "pct_total_conversions": 9.92,
      "lift": 0.99
    },
    "decil_6": {
      "total_leads": 1174,
      "conversions": 12,
      "conversion_rate": 0.0102,
      "pct_total_conversions": 9.92,
      "lift": 0.99
    },
    "decil_7": {
      "total_leads": 1173,
      "conversions": 15,
      "conversion_rate": 0.0128,
      "pct_total_conversions": 12.4,
      "lift": 1.24
    },
    "decil_8": {
      "total_leads": 1174,
      "conversions": 16,
      "conversion_rate": 0.0136,
      "pct_total_conversions": 13.22,
      "lift": 1.32
    },
    "decil_9": {
      "total_leads": 1173,
      "conversions": 16,
      "conversion_rate": 0.0136,
      "pct_total_conversions": 13.22,
      "lift": 1.32
    },
    "decil_10": {
      "total_leads": 1174,
      "conversions": 23,
      "conversion_rate": 0.0196,
      "pct_total_conversions": 19.01,
      "lift": 1.9
    }
  },
  "production_notes": {
    "use_case": "Lead scoring for DevClub products with budget allocation optimization",
    "prediction_interpretation": "Higher probability = higher priority for budget allocation",
    "calibration_status": "Not calibrated - use for ranking only",
    "recommended_deployment": "Batch scoring with validation on future launches",
    "monitoring_requirements": "Track performance degradation and feature drift",
    "model_limitations": "Monotonia at 100.0% - investigate if < 80%"
  }
}